template_project_utils/__init__.py
template_project_utils/__main__.py
template_project_utils/_version.py
template_project_utils/git.py
template_project_utils/keyword_scanner.py
template_project_utils/main.py
template_project_utils/template_initializer.py
template_project_utils/resources/configs/default_logging_config.yaml
template_project_utils/resources/schemas/config.json
template_project_utils-0.2.1.dist-info/LICENSE
template_project_utils-0.2.1.dist-info/METADATA
template_project_utils-0.2.1.dist-info/WHEEL
template_project_utils-0.2.1.dist-info/entry_points.txt
template_project_utils-0.2.1.dist-info/top_level.txt
template_project_utils-0.2.1.dist-info/RECORD
