Metadata-Version: 2.1
Name: template_project_utils
Version: 0.2.1
Summary: Utilities to initialize template projects (replacing names, renaming/removing files.
Home-page: https://github.com/twyleg/template_project_utils
Author: Torsten Wylegala
Author-email: mail@twyleg.de
License: GPL 3.0
License-File: LICENSE
Requires-Dist: simple-python-app ==0.3.0
Requires-Dist: pygit2 ~=1.15.1
Requires-Dist: inquirerpy ~=0.3.4
